{
  "045210805048": {
    "VacationDays": 15,
    "Grade": 4.6,
    "DoctorSpecialization": 2,
    "VacationPeriods": [],
    "Name": "Tara",
    "LastName": "Pogančev",
    "Jmbg": "045210805048",
    "Username": "l",
    "Password": "l",
    "Email": "tarapogancev@gmail.com",
    "Phone": "629998425",
    "Address": {
      "City": {
        "Name": "Novi Sad",
        "PostalCode": 21000,
        "Country": {
          "Name": "Srbija"
        }
      },
      "Street": "Bulevar Despota Stefana",
      "Number": "7"
    },
    "Serialize": true
  },
  "4848555021548": {
    "VacationDays": 20,
    "Grade": 5.0,
    "DoctorSpecialization": 4,
    "VacationPeriods": [],
    "Name": "Zack",
    "LastName": "Fair",
    "Jmbg": "4848555021548",
    "Username": "zack",
    "Password": "l",
    "Email": "zackfair@zdravo.com",
    "Phone": "0698547521",
    "Address": {
      "City": {
        "Name": "Midgar",
        "PostalCode": 99888,
        "Country": {
          "Name": "Gaia"
        }
      },
      "Street": "Shinra Inc",
      "Number": "Floor 75"
    },
    "Serialize": true
  },
  "22157484654211": {
    "VacationDays": 18,
    "Grade": 0.0,
    "DoctorSpecialization": 0,
    "VacationPeriods": [],
    "Name": "Cloud",
    "LastName": "Strife",
    "Jmbg": "22157484654211",
    "Username": "cloud",
    "Password": "l",
    "Email": "fluffy@clouds.com",
    "Phone": "0640005481",
    "Address": {
      "City": {
        "Name": "Nibelheim",
        "PostalCode": 33654,
        "Country": {
          "Name": "Gaia"
        }
      },
      "Street": "Main Town Square",
      "Number": "5"
    },
    "Serialize": true
  },
  "484855502123": {
    "VacationDays": 20,
    "Grade": 0.0,
    "DoctorSpecialization": 0,
    "VacationPeriods": [],
    "Name": "Katarina",
    "LastName": "Gavrić",
    "Jmbg": "484855502123",
    "Username": "katarina",
    "Password": "l",
    "Email": "zackfair@zdravo.com",
    "Phone": "0698547521",
    "Address": {
      "City": {
        "Name": "Novi Sad",
        "PostalCode": 23300,
        "Country": {
          "Name": "Srbija"
        }
      },
      "Street": "Alekse Šantića",
      "Number": "75"
    },
    "Serialize": true
  },
  "4848512502123": {
    "VacationDays": 20,
    "Grade": 0.0,
    "DoctorSpecialization": 0,
    "VacationPeriods": [],
    "Name": "Marija",
    "LastName": "Radović",
    "Jmbg": "4848512502123",
    "Username": "marija",
    "Password": "l",
    "Email": "zackfair@zdravo.com",
    "Phone": "0698547521",
    "Address": {
      "City": {
        "Name": "Novi Sad",
        "PostalCode": 23300,
        "Country": {
          "Name": "Srbija"
        }
      },
      "Street": "Gogoljeva",
      "Number": "10"
    },
    "Serialize": true
  }
}